easyweather/__init__.py
easyweather/easymetar.py
easyweather-0.0.1.dist-info/METADATA
easyweather-0.0.1.dist-info/WHEEL
easyweather-0.0.1.dist-info/top_level.txt
easyweather-0.0.1.dist-info/RECORD
