Metadata-Version: 2.1
Name: easyweather
Version: 0.0.1
Summary: A simple utility to get METAR information from the NWSs website. Uses bs4
Home-page: UNKNOWN
Author: ThomasV2
Author-email: UNKNOWN
License: UNKNOWN
Keywords: python,video,stream,video stream,camera stream,sockets
Platform: UNKNOWN
Classifier: Development Status :: 1 - Planning
Classifier: Intended Audience :: Developers
Classifier: Programming Language :: Python :: 3
Classifier: Operating System :: Unix
Classifier: Operating System :: MacOS :: MacOS X
Classifier: Operating System :: Microsoft :: Windows
Requires-Dist: bs4
Requires-Dist: urllib.request.urlopen
